douyin_live_chat/__init__.py
douyin_live_chat/core.py
douyin_live_chat/sign.js
douyin_live_chat/sign_v0.js
douyin_live_chat/protobuf/__init__.py
douyin_live_chat/protobuf/douyin.proto
douyin_live_chat/protobuf/douyin.py
douyin_live_chat/protobuf/readme.md
douyin_live_chat-1.0.4.dist-info/METADATA
douyin_live_chat-1.0.4.dist-info/WHEEL
douyin_live_chat-1.0.4.dist-info/top_level.txt
douyin_live_chat-1.0.4.dist-info/RECORD
